{
  "_version": "1.0.0",
  "_description": "阵营连携效果配置 — 5阵营(Human/Elf/Orc/Undead/Mech)，每阵营2/3/4人激活阈值",
  "_note": "与 FactionSynergiesConfig / FactionSynergyEntry 对应，由 ConfigLoader.LoadFactionSynergies() 加载",
  "synergies": [
    {
      "id": "human_alliance_2",
      "name_cn": "人类联盟",
      "faction": "Human",
      "required_count": 2,
      "effect": "all_allies attack +10%",
      "target": "all_allies",
      "attack_bonus_pct": 0.1,
      "defense_bonus_pct": 0.0,
      "speed_bonus_pct": 0.0,
      "crit_rate_bonus_pct": 0.0,
      "hp_regen_pct": 0.0,
      "all_stats_bonus_pct": 0.0
    },
    {
      "id": "human_rally_3",
      "name_cn": "王族集结",
      "faction": "Human",
      "required_count": 3,
      "effect": "all_allies attack +15%, defense +10%",
      "target": "all_allies",
      "attack_bonus_pct": 0.15,
      "defense_bonus_pct": 0.1,
      "speed_bonus_pct": 0.0,
      "crit_rate_bonus_pct": 0.0,
      "hp_regen_pct": 0.0,
      "all_stats_bonus_pct": 0.0
    },
    {
      "id": "human_empire_4",
      "name_cn": "帝国荣耀",
      "faction": "Human",
      "required_count": 4,
      "effect": "all_allies all_stats +15%, hp_regen 5% per round",
      "target": "all_allies",
      "attack_bonus_pct": 0.0,
      "defense_bonus_pct": 0.0,
      "speed_bonus_pct": 0.0,
      "crit_rate_bonus_pct": 0.0,
      "hp_regen_pct": 0.05,
      "all_stats_bonus_pct": 0.15
    },
    {
      "id": "elf_resonance_2",
      "name_cn": "精灵共鸣",
      "faction": "Elf",
      "required_count": 2,
      "effect": "self_faction speed +15%",
      "target": "self_faction",
      "attack_bonus_pct": 0.0,
      "defense_bonus_pct": 0.0,
      "speed_bonus_pct": 0.15,
      "crit_rate_bonus_pct": 0.0,
      "hp_regen_pct": 0.0,
      "all_stats_bonus_pct": 0.0
    },
    {
      "id": "elf_blessing_3",
      "name_cn": "自然祝福",
      "faction": "Elf",
      "required_count": 3,
      "effect": "self_faction speed +20%, hp_regen 5% per round",
      "target": "self_faction",
      "attack_bonus_pct": 0.0,
      "defense_bonus_pct": 0.0,
      "speed_bonus_pct": 0.2,
      "crit_rate_bonus_pct": 0.0,
      "hp_regen_pct": 0.05,
      "all_stats_bonus_pct": 0.0
    },
    {
      "id": "elf_ancient_4",
      "name_cn": "远古之森",
      "faction": "Elf",
      "required_count": 4,
      "effect": "self_faction all_stats +20%, speed +25%, hp_regen 8% per round",
      "target": "self_faction",
      "attack_bonus_pct": 0.0,
      "defense_bonus_pct": 0.0,
      "speed_bonus_pct": 0.25,
      "crit_rate_bonus_pct": 0.0,
      "hp_regen_pct": 0.08,
      "all_stats_bonus_pct": 0.2
    },
    {
      "id": "orc_fury_2",
      "name_cn": "兽人狂暴",
      "faction": "Orc",
      "required_count": 2,
      "effect": "self_faction attack +20%",
      "target": "self_faction",
      "attack_bonus_pct": 0.2,
      "defense_bonus_pct": 0.0,
      "speed_bonus_pct": 0.0,
      "crit_rate_bonus_pct": 0.0,
      "hp_regen_pct": 0.0,
      "all_stats_bonus_pct": 0.0
    },
    {
      "id": "orc_waaagh_3",
      "name_cn": "WAAAGH!",
      "faction": "Orc",
      "required_count": 3,
      "effect": "self_faction attack +30%, crit_rate +10%",
      "target": "self_faction",
      "attack_bonus_pct": 0.3,
      "defense_bonus_pct": 0.0,
      "speed_bonus_pct": 0.0,
      "crit_rate_bonus_pct": 0.1,
      "hp_regen_pct": 0.0,
      "all_stats_bonus_pct": 0.0
    },
    {
      "id": "orc_berserker_4",
      "name_cn": "狂战之魂",
      "faction": "Orc",
      "required_count": 4,
      "effect": "self_faction attack +40%, crit_rate +20%, all_stats +15%",
      "target": "self_faction",
      "attack_bonus_pct": 0.4,
      "defense_bonus_pct": 0.0,
      "speed_bonus_pct": 0.0,
      "crit_rate_bonus_pct": 0.2,
      "hp_regen_pct": 0.0,
      "all_stats_bonus_pct": 0.15
    },
    {
      "id": "undead_corruption_2",
      "name_cn": "亡灵侵蚀",
      "faction": "Undead",
      "required_count": 2,
      "effect": "self_faction crit_rate +15%",
      "target": "self_faction",
      "attack_bonus_pct": 0.0,
      "defense_bonus_pct": 0.0,
      "speed_bonus_pct": 0.0,
      "crit_rate_bonus_pct": 0.15,
      "hp_regen_pct": 0.0,
      "all_stats_bonus_pct": 0.0
    },
    {
      "id": "undead_plague_3",
      "name_cn": "瘟疫蔓延",
      "faction": "Undead",
      "required_count": 3,
      "effect": "self_faction crit_rate +20%, attack +15%, hp_regen 5% per round",
      "target": "self_faction",
      "attack_bonus_pct": 0.15,
      "defense_bonus_pct": 0.0,
      "speed_bonus_pct": 0.0,
      "crit_rate_bonus_pct": 0.2,
      "hp_regen_pct": 0.05,
      "all_stats_bonus_pct": 0.0
    },
    {
      "id": "undead_lich_4",
      "name_cn": "巫妖之王",
      "faction": "Undead",
      "required_count": 4,
      "effect": "all_allies crit_rate +25%, attack +20%, hp_regen 8% per round",
      "target": "all_allies",
      "attack_bonus_pct": 0.2,
      "defense_bonus_pct": 0.0,
      "speed_bonus_pct": 0.0,
      "crit_rate_bonus_pct": 0.25,
      "hp_regen_pct": 0.08,
      "all_stats_bonus_pct": 0.0
    },
    {
      "id": "mech_overload_2",
      "name_cn": "机械过载",
      "faction": "Mech",
      "required_count": 2,
      "effect": "self_faction defense +25%",
      "target": "self_faction",
      "attack_bonus_pct": 0.0,
      "defense_bonus_pct": 0.25,
      "speed_bonus_pct": 0.0,
      "crit_rate_bonus_pct": 0.0,
      "hp_regen_pct": 0.0,
      "all_stats_bonus_pct": 0.0
    },
    {
      "id": "mech_fortress_3",
      "name_cn": "钢铁堡垒",
      "faction": "Mech",
      "required_count": 3,
      "effect": "self_faction defense +35%, all_stats +10%, hp_regen 5% per round",
      "target": "self_faction",
      "attack_bonus_pct": 0.0,
      "defense_bonus_pct": 0.35,
      "speed_bonus_pct": 0.0,
      "crit_rate_bonus_pct": 0.0,
      "hp_regen_pct": 0.05,
      "all_stats_bonus_pct": 0.1
    },
    {
      "id": "mech_awakening_4",
      "name_cn": "觉醒协议",
      "faction": "Mech",
      "required_count": 4,
      "effect": "self_faction all_stats +25%, defense +40%, hp_regen 10% per round",
      "target": "self_faction",
      "attack_bonus_pct": 0.0,
      "defense_bonus_pct": 0.4,
      "speed_bonus_pct": 0.0,
      "crit_rate_bonus_pct": 0.0,
      "hp_regen_pct": 0.1,
      "all_stats_bonus_pct": 0.25
    }
  ],
  "_reserved": {}
}
